viron/__init__.py
viron/tests.py
viron/viron.py
viron-0.6.0.dist-info/DESCRIPTION.rst
viron-0.6.0.dist-info/entry_points.txt
viron-0.6.0.dist-info/METADATA
viron-0.6.0.dist-info/metadata.json
viron-0.6.0.dist-info/pbr.json
viron-0.6.0.dist-info/RECORD
viron-0.6.0.dist-info/top_level.txt
viron-0.6.0.dist-info/WHEEL
