Metadata-Version: 2.0
Name: viron
Version: 0.6.0
Summary: Put environment variables in text file templates.
Home-page: http://github.com/fish2000/viron/
Author: Alexander Bohn
Author-email: fish2000@gmail.com
License: MIT
Download-URL: http://github.com/fish2000/viron/zipball/master
Keywords: python environment variable simple template text
Platform: any
Classifier: Development Status :: 5 - Production/Stable
Classifier: License :: OSI Approved :: MIT License
Classifier: Operating System :: MacOS
Classifier: Operating System :: Microsoft :: Windows
Classifier: Operating System :: OS Independent
Classifier: Operating System :: POSIX
Classifier: Operating System :: Unix
Classifier: Programming Language :: Python :: 2.7
Classifier: Programming Language :: Python :: 3.3
Requires-Dist: argparse
Requires-Dist: argh (>=0.26.1)
